CodersWheel/__init__.py
CodersWheel/ConnectorWheel/__init__.py
CodersWheel/ConnectorWheel/db_core/MysqlConnector.py
CodersWheel/ConnectorWheel/db_core/Redisconnector.py
CodersWheel/ConnectorWheel/db_core/__init__.py
CodersWheel/ConnectorWheel/db_core/asnyc_mysql_connector.py
CodersWheel/Core/Combine.py
CodersWheel/Core/Core.py
CodersWheel/Core/__init__.py
CodersWheel/OtherToolWheel/AboutDB.py
CodersWheel/OtherToolWheel/AboutDate.py
CodersWheel/OtherToolWheel/AboutSqlite.py
CodersWheel/OtherToolWheel/CacheFunctions.py
CodersWheel/OtherToolWheel/DataFeatureScaling.py
CodersWheel/OtherToolWheel/Luhn.py
CodersWheel/OtherToolWheel/MysqlConnector.py
CodersWheel/OtherToolWheel/Needleman_Wunsch.py
CodersWheel/OtherToolWheel/Scheduler.py
CodersWheel/OtherToolWheel/SeriesComparing.py
CodersWheel/OtherToolWheel/Tools.py
CodersWheel/OtherToolWheel/Wrappers.py
CodersWheel/OtherToolWheel/__init__.py
CodersWheel/OtherToolWheel/coroutine_prev_active_decor.py
CodersWheel/QuickTool/MySQLConn_v004_node.py
CodersWheel/QuickTool/MySQLConn_v005_node.py
CodersWheel/QuickTool/__init__.py
CodersWheel/QuickTool/boost_up.py
CodersWheel/QuickTool/ch2pandas.py
CodersWheel/QuickTool/ch2pandas_node.py
CodersWheel/QuickTool/check_file_type.py
CodersWheel/QuickTool/detect_file_path.py
CodersWheel/QuickTool/excel_format_parser.py
CodersWheel/QuickTool/file_cache.py
CodersWheel/QuickTool/generate_str_node.py
CodersWheel/QuickTool/importer.py
CodersWheel/QuickTool/lazy_load.py
CodersWheel/QuickTool/logger.py
CodersWheel/QuickTool/process_bar.py
CodersWheel/QuickTool/retry_it.py
CodersWheel/QuickTool/singleton.py
CodersWheel/QuickTool/task_test_all.py
CodersWheel/QuickTool/tasks_register.py
CodersWheel/QuickTool/timer.py
CodersWheel/QuickTool/typeassert.py
CodersWheel/ServiceWheel/CoroutineBoostup.py
CodersWheel/ServiceWheel/Service.py
CodersWheel/ServiceWheel/__init__.py
CodersWheel/api/API.py
CodersWheel/api/Wheel.py
CodersWheel/api/__init__.py
test/__init__.py
CodersWheel-0.2.1.dist-info/LICENSE
CodersWheel-0.2.1.dist-info/METADATA
CodersWheel-0.2.1.dist-info/WHEEL
CodersWheel-0.2.1.dist-info/top_level.txt
CodersWheel-0.2.1.dist-info/RECORD
