Metadata-Version: 2.1
Name: CodersWheel
Version: 0.2.1
Summary: CodersWheel - CW
Home-page: https://github.com/sn0wfree
Author: s & n & 0 & w & f & r & e & e
Author-email: snowfreedom0815@gmail.com
License: MIT
License-File: LICENSE
